qwsend/__init__.py
qwsend/cli.py
qwsend/client.py
qwsend/exceptions.py
qwsend/version.py
qwsend-0.2.1.dist-info/licenses/LICENSE
qwsend-0.2.1.dist-info/METADATA
qwsend-0.2.1.dist-info/WHEEL
qwsend-0.2.1.dist-info/entry_points.txt
qwsend-0.2.1.dist-info/top_level.txt
qwsend-0.2.1.dist-info/RECORD
