Metadata-Version: 2.4
Name: qwsend
Version: 0.2.1
Summary: A lightweight WeCom (WeChat Work) webhook client using httpx with custom User-Agent
Author-email: Sam Song <samsong@stu.njau.edu.cn>
License-Expression: MIT
Project-URL: Homepage, https://github.com/ZhulongNT/qwsend
Project-URL: Issues, https://github.com/ZhulongNT/qwsend/issuesgi
Keywords: wecom,wechat-work,webhook,httpx
Classifier: Programming Language :: Python :: 3
Classifier: Programming Language :: Python :: 3 :: Only
Classifier: Programming Language :: Python :: 3.8
Classifier: Programming Language :: Python :: 3.9
Classifier: Programming Language :: Python :: 3.10
Classifier: Programming Language :: Python :: 3.11
Classifier: Programming Language :: Python :: 3.12
Classifier: Programming Language :: Python :: 3.13
Classifier: Programming Language :: Python :: 3.14
Classifier: Intended Audience :: Developers
Classifier: Topic :: Internet :: WWW/HTTP
Classifier: Topic :: Software Development :: Libraries :: Python Modules
Requires-Python: >=3.8
License-File: LICENSE
Requires-Dist: httpx<0.28,>=0.24
Provides-Extra: dev
Requires-Dist: pytest>=7; extra == "dev"
Dynamic: license-file
